ottar/__init__.py
ottar/_version.py
ottar/ottar.py
OTTAR-0.7.0.dist-info/LICENSE
OTTAR-0.7.0.dist-info/METADATA
OTTAR-0.7.0.dist-info/WHEEL
OTTAR-0.7.0.dist-info/top_level.txt
OTTAR-0.7.0.dist-info/RECORD
