Metadata-Version: 2.1
Name: OTTAR
Version: 0.7.0
Summary: Ode To Transient Ancho de los Rivers: Transient evolution of river-channel width
Home-page: https://github.com/MNiMORPH/ottar
Author: Andrew D. Wickert
Author-email: awickert@umn.edu
Project-URL: Source and README, https://github.com/MNiMORPH/OTTAR
Project-URL: CSDMS repository, https://csdms.colorado.edu/wiki/Model:OTTAR
Project-URL: Zenodo, https://zenodo.org/record/5781792/export/dcat#.Yme_nIyxXCK
Project-URL: DOI, https://dx.doi.org/10.5281/zenodo.5124965
Keywords: fluvial geomorphology sediment transport landscape evolution
Classifier: Programming Language :: Python :: 3
Classifier: License :: OSI Approved :: GNU General Public License v3 (GPLv3)
Classifier: Operating System :: OS Independent
Classifier: Topic :: Scientific/Engineering :: Hydrology
Classifier: Intended Audience :: Science/Research
License-File: LICENSE
Requires-Dist: matplotlib
Requires-Dist: numpy
Requires-Dist: pandas
Requires-Dist: scipy
